premise/__init__.py
premise/activity_maps.py
premise/battery.py
premise/biomass.py
premise/brightway2.py
premise/brightway25.py
premise/carbon_dioxide_removal.py
premise/cement.py
premise/clean_datasets.py
premise/data_collection.py
premise/electricity.py
premise/emissions.py
premise/export.py
premise/external.py
premise/external_data_validation.py
premise/filesystem_constants.py
premise/final_energy.py
premise/geomap.py
premise/heat.py
premise/incremental.py
premise/inventory_imports.py
premise/logger.py
premise/marginal_mixes.py
premise/metals.py
premise/mining.py
premise/new_database.py
premise/pathways.py
premise/renewables.py
premise/report.py
premise/scenario_downloader.py
premise/score_comparison.py
premise/steel.py
premise/transformation.py
premise/transport.py
premise/utils.py
premise/validation.py
premise/data/GAINS_emission_factors/GAINS_ei_pollutants.yaml
premise/data/GAINS_emission_factors/gains_ecoinvent_sectoral_mapping.yaml
premise/data/GAINS_emission_factors/iam_data/CLE/CH4.csv
premise/data/GAINS_emission_factors/iam_data/CLE/N2O.csv
premise/data/GAINS_emission_factors/iam_data/CLE/NH3.csv
premise/data/GAINS_emission_factors/iam_data/CLE/NOx.csv
premise/data/GAINS_emission_factors/iam_data/CLE/PM1.csv
premise/data/GAINS_emission_factors/iam_data/CLE/PM10.csv
premise/data/GAINS_emission_factors/iam_data/CLE/PM25.csv
premise/data/GAINS_emission_factors/iam_data/CLE/PM_BC.csv
premise/data/GAINS_emission_factors/iam_data/CLE/PM_OC.csv
premise/data/GAINS_emission_factors/iam_data/CLE/PM_TSP.csv
premise/data/GAINS_emission_factors/iam_data/CLE/SO2.csv
premise/data/GAINS_emission_factors/iam_data/CLE/VOC.csv
premise/data/GAINS_emission_factors/iam_data/MFR/CH4.csv
premise/data/GAINS_emission_factors/iam_data/MFR/N2O.csv
premise/data/GAINS_emission_factors/iam_data/MFR/NH3.csv
premise/data/GAINS_emission_factors/iam_data/MFR/NOx.csv
premise/data/GAINS_emission_factors/iam_data/MFR/PM1.csv
premise/data/GAINS_emission_factors/iam_data/MFR/PM10.csv
premise-2.3.6.dist-info/licenses/LICENSE
premise-2.3.6.dist-info/METADATA
premise-2.3.6.dist-info/WHEEL
premise-2.3.6.dist-info/top_level.txt
premise-2.3.6.dist-info/RECORD
