Metadata-Version: 2.4
Name: premise
Version: 2.3.6
Summary: Coupling IAM output to ecoinvent LCA database ecoinvent for prospective LCA
Author-email: Romain Sacchi <romain.sacchi@psi.ch>, Alois Dirnaichner <dirnaichner@pik-potsdam.de>, Chris Mutel <cmutel@gmail.com>, Alvaro Hahn Menacho <alvaro.hahn-menacho@psi.ch>
Maintainer-email: Romain Sacchi <romain.sacchi@psi.ch>
Project-URL: source, https://github.com/polca/premise
Project-URL: homepage, https://github.com/polca/premise
Project-URL: tracker, https://github.com/polca/premise/issues
Classifier: Intended Audience :: Science/Research
Classifier: License :: OSI Approved :: BSD License
Classifier: Natural Language :: English
Classifier: Programming Language :: Python :: 3
Classifier: Operating System :: OS Independent
Classifier: Topic :: Scientific/Engineering
Requires-Python: >=3.10
License-File: LICENSE
Requires-Dist: numpy<2.0.0
Requires-Dist: bottleneck
Requires-Dist: bw2data
Requires-Dist: bw2io
Requires-Dist: ecoinvent_interface
Requires-Dist: constructive-geometries>=1.0.0
Requires-Dist: cryptography
Requires-Dist: datapackage
Requires-Dist: pandas<3.0.0
Requires-Dist: platformdirs
Requires-Dist: premise_gwp
Requires-Dist: prettytable
Requires-Dist: pyarrow
Requires-Dist: pycountry
Requires-Dist: pyYaml
Requires-Dist: requests
Requires-Dist: schema
Requires-Dist: scipy<1.14.0
Requires-Dist: sparse>=0.14.0
Requires-Dist: wurst>=0.4
Requires-Dist: xarray<=2024.2.0
Requires-Dist: tqdm
Requires-Dist: unfold
Provides-Extra: docs
Requires-Dist: sphinx-rtd-theme; extra == "docs"
Provides-Extra: bw25
Requires-Dist: bw2calc>=2.0.1; extra == "bw25"
Requires-Dist: bw2data>=4.3; extra == "bw25"
Requires-Dist: bw2io>=0.9.4; extra == "bw25"
Requires-Dist: bottleneck; extra == "bw25"
Requires-Dist: ecoinvent_interface; extra == "bw25"
Requires-Dist: constructive-geometries>=0.9.5; extra == "bw25"
Requires-Dist: numpy<2.0.0; extra == "bw25"
Requires-Dist: cryptography; extra == "bw25"
Requires-Dist: datapackage; extra == "bw25"
Requires-Dist: pandas; extra == "bw25"
Requires-Dist: platformdirs; extra == "bw25"
Requires-Dist: premise_gwp; extra == "bw25"
Requires-Dist: prettytable; extra == "bw25"
Requires-Dist: pyarrow; extra == "bw25"
Requires-Dist: pycountry; extra == "bw25"
Requires-Dist: pyYaml; extra == "bw25"
Requires-Dist: requests; extra == "bw25"
Requires-Dist: schema; extra == "bw25"
Requires-Dist: scipy<1.14.0; extra == "bw25"
Requires-Dist: sparse>=0.14.0; extra == "bw25"
Requires-Dist: wurst>=0.4; extra == "bw25"
Requires-Dist: xarray<=2024.2.0; extra == "bw25"
Requires-Dist: tqdm; extra == "bw25"
Requires-Dist: unfold; extra == "bw25"
Provides-Extra: bw2
Requires-Dist: bw2calc==1.8.2; extra == "bw2"
Requires-Dist: bw2data==3.6.6; extra == "bw2"
Requires-Dist: bw2io==0.8.12; extra == "bw2"
Requires-Dist: bottleneck; extra == "bw2"
Requires-Dist: ecoinvent_interface; extra == "bw2"
Requires-Dist: constructive-geometries>=0.9.5; extra == "bw2"
Requires-Dist: numpy<2.0.0; extra == "bw2"
Requires-Dist: cryptography; extra == "bw2"
Requires-Dist: datapackage; extra == "bw2"
Requires-Dist: pandas; extra == "bw2"
Requires-Dist: platformdirs; extra == "bw2"
Requires-Dist: premise_gwp; extra == "bw2"
Requires-Dist: prettytable; extra == "bw2"
Requires-Dist: pyarrow; extra == "bw2"
Requires-Dist: pycountry; extra == "bw2"
Requires-Dist: pyYaml; extra == "bw2"
Requires-Dist: requests; extra == "bw2"
Requires-Dist: schema; extra == "bw2"
Requires-Dist: sparse>=0.14.0; extra == "bw2"
Requires-Dist: wurst>=0.4; extra == "bw2"
Requires-Dist: xarray<=2024.2.0; extra == "bw2"
Requires-Dist: tqdm; extra == "bw2"
Requires-Dist: unfold; extra == "bw2"
Dynamic: license-file
